{"lastUsed":1603646302868,"path":"C:\/Users\/marwa\/eclipse-workspace","projectCount":7,"recentFiles":[{"path":"\/HRMS-CUCUMBER\/src\/test\/java\/com\/hrms\/testbase","parentWorkspace":"C:\/Users\/marwa\/eclipse-workspace","name":"PageInitializer.java","lastModified":1600055695974,"locationURI":"file:\/C:\/Users\/marwa\/eclipse-workspace\/HRMS-CUCUMBER\/src\/test\/java\/com\/hrms\/testbase\/PageInitializer.java"},{"path":"\/HRMS-CUCUMBER\/src\/test\/java\/com\/hrms\/utils","parentWorkspace":"C:\/Users\/marwa\/eclipse-workspace","name":"Constants.java","lastModified":1596825728175,"locationURI":"file:\/C:\/Users\/marwa\/eclipse-workspace\/HRMS-CUCUMBER\/src\/test\/java\/com\/hrms\/utils\/Constants.java"},{"path":"\/HRMS-CUCUMBER\/src\/test\/resources\/Features","parentWorkspace":"C:\/Users\/marwa\/eclipse-workspace","name":"Login_old.feature","lastModified":1600352525608,"locationURI":"file:\/C:\/Users\/marwa\/eclipse-workspace\/HRMS-CUCUMBER\/src\/test\/resources\/Features\/Login_old.feature"},{"path":"\/HRMS-CUCUMBER\/src\/test\/resources\/Features","parentWorkspace":"C:\/Users\/marwa\/eclipse-workspace","name":"nameValidationinDB.feature","lastModified":1600057353974,"locationURI":"file:\/C:\/Users\/marwa\/eclipse-workspace\/HRMS-CUCUMBER\/src\/test\/resources\/Features\/nameValidationinDB.feature"},{"path":"\/JavaPractice\/src\/OOP","parentWorkspace":"C:\/Users\/marwa\/eclipse-workspace","name":"Inheritance.java","lastModified":1603469766357,"locationURI":"file:\/C:\/Users\/marwa\/eclipse-workspace\/JavaPractice\/src\/OOP\/Inheritance.java"},{"path":"\/HRMS-CUCUMBER\/src\/test\/java\/comhrms\/API\/utils","parentWorkspace":"C:\/Users\/marwa\/eclipse-workspace","name":"APIConstants.java","lastModified":1599590950085,"locationURI":"file:\/C:\/Users\/marwa\/eclipse-workspace\/HRMS-CUCUMBER\/src\/test\/java\/comhrms\/API\/utils\/APIConstants.java"},{"path":"\/com.syntax.Selenium\/src\/com\/syntax\/selenuim\/class0901","parentWorkspace":"C:\/Users\/marwa\/eclipse-workspace","name":"HW1.java","lastModified":1590802479975,"locationURI":"file:\/C:\/Users\/marwa\/eclipse-workspace\/com.syntax.Selenium\/src\/com\/syntax\/selenuim\/class0901\/HW1.java"},{"path":"\/HRMS-CUCUMBER\/src\/test\/java\/com\/hrms\/utils","parentWorkspace":"C:\/Users\/marwa\/eclipse-workspace","name":"ExcelUtility.java","lastModified":1597686499427,"locationURI":"file:\/C:\/Users\/marwa\/eclipse-workspace\/HRMS-CUCUMBER\/src\/test\/java\/com\/hrms\/utils\/ExcelUtility.java"},{"path":"\/KGB\/src\/test\/java\/com\/hrms\/steps","parentWorkspace":"C:\/Users\/marwa\/eclipse-workspace","name":"EmployeeSearchSteps.java","lastModified":1596900219003,"locationURI":"file:\/C:\/Users\/marwa\/eclipse-workspace\/KGB\/src\/test\/java\/com\/hrms\/steps\/EmployeeSearchSteps.java"},{"path":"\/HRMS-CUCUMBER\/src\/test\/resources\/Features","parentWorkspace":"C:\/Users\/marwa\/eclipse-workspace","name":"SauceDemo.feature","lastModified":1599007833587,"locationURI":"file:\/C:\/Users\/marwa\/eclipse-workspace\/HRMS-CUCUMBER\/src\/test\/resources\/Features\/SauceDemo.feature"},{"path":"\/HRMSFramework\/src\/test\/java\/com\/hrms\/testcases","parentWorkspace":"C:\/Users\/marwa\/eclipse-workspace","name":"LoginTest.java","lastModified":1596823603377,"locationURI":"file:\/C:\/Users\/marwa\/eclipse-workspace\/HRMSFramework\/src\/test\/java\/com\/hrms\/testcases\/LoginTest.java"},{"path":"\/HRMS-CUCUMBER\/src\/test\/java\/com\/hrms\/runners","parentWorkspace":"C:\/Users\/marwa\/eclipse-workspace","name":"smoke.java","lastModified":1598724267603,"locationURI":"file:\/C:\/Users\/marwa\/eclipse-workspace\/HRMS-CUCUMBER\/src\/test\/java\/com\/hrms\/runners\/smoke.java"},{"path":"\/HRMS-CUCUMBER\/src\/test\/java\/comhrms\/API\/utils","parentWorkspace":"C:\/Users\/marwa\/eclipse-workspace","name":"PayloadConstants.java","lastModified":1599769898780,"locationURI":"file:\/C:\/Users\/marwa\/eclipse-workspace\/HRMS-CUCUMBER\/src\/test\/java\/comhrms\/API\/utils\/PayloadConstants.java"},{"path":"\/com.syntax.Selenium\/src\/com\/pages","parentWorkspace":"C:\/Users\/marwa\/eclipse-workspace","name":"LoginPageElement.java","lastModified":1590956434249,"locationURI":"file:\/C:\/Users\/marwa\/eclipse-workspace\/com.syntax.Selenium\/src\/com\/pages\/LoginPageElement.java"},{"path":"\/HRMS-CUCUMBER\/src\/test\/java\/com\/hrms\/steps","parentWorkspace":"C:\/Users\/marwa\/eclipse-workspace","name":"DashboardSteps.java","lastModified":1598730360749,"locationURI":"file:\/C:\/Users\/marwa\/eclipse-workspace\/HRMS-CUCUMBER\/src\/test\/java\/com\/hrms\/steps\/DashboardSteps.java"},{"path":"\/HRMSFramework","parentWorkspace":"C:\/Users\/marwa\/eclipse-workspace","name":"Smoke.xml","lastModified":1596665798495,"locationURI":"file:\/C:\/Users\/marwa\/eclipse-workspace\/HRMSFramework\/Smoke.xml"},{"path":"\/HRMS-CUCUMBER\/src\/test\/java\/com\/hrms\/steps","parentWorkspace":"C:\/Users\/marwa\/eclipse-workspace","name":"EmployeeSearchSteps.java","lastModified":1600057353264,"locationURI":"file:\/C:\/Users\/marwa\/eclipse-workspace\/HRMS-CUCUMBER\/src\/test\/java\/com\/hrms\/steps\/EmployeeSearchSteps.java"},{"path":"\/HRMS-CUCUMBER\/src\/test\/java\/com\/hrms\/steps","parentWorkspace":"C:\/Users\/marwa\/eclipse-workspace","name":"Hooks.java","lastModified":1598880849040,"locationURI":"file:\/C:\/Users\/marwa\/eclipse-workspace\/HRMS-CUCUMBER\/src\/test\/java\/com\/hrms\/steps\/Hooks.java"},{"path":"\/KGB\/src\/test\/java\/com\/hrms\/steps","parentWorkspace":"C:\/Users\/marwa\/eclipse-workspace","name":"marwafeatures.java","lastModified":1596387622816,"locationURI":"file:\/C:\/Users\/marwa\/eclipse-workspace\/KGB\/src\/test\/java\/com\/hrms\/steps\/marwafeatures.java"},{"path":"\/com.syntax.Selenium\/src\/com\/syntax\/utils","parentWorkspace":"C:\/Users\/marwa\/eclipse-workspace","name":"BaseClass.java","lastModified":1590939402332,"locationURI":"file:\/C:\/Users\/marwa\/eclipse-workspace\/com.syntax.Selenium\/src\/com\/syntax\/utils\/BaseClass.java"},{"path":"\/HRMSFramework\/src\/test\/java\/com\/hrms\/testbase","parentWorkspace":"C:\/Users\/marwa\/eclipse-workspace","name":"BaseClass.java","lastModified":1596823603377,"locationURI":"file:\/C:\/Users\/marwa\/eclipse-workspace\/HRMSFramework\/src\/test\/java\/com\/hrms\/testbase\/BaseClass.java"},{"path":"\/KGB\/src\/test\/java\/com\/hrms\/pages","parentWorkspace":"C:\/Users\/marwa\/eclipse-workspace","name":"ViewEmployeePageElements.java","lastModified":1596831571639,"locationURI":"file:\/C:\/Users\/marwa\/eclipse-workspace\/KGB\/src\/test\/java\/com\/hrms\/pages\/ViewEmployeePageElements.java"},{"path":"\/KGB\/src\/test\/java\/com\/hrms\/testbase","parentWorkspace":"C:\/Users\/marwa\/eclipse-workspace","name":"PageInitializer.java","lastModified":1596900309011,"locationURI":"file:\/C:\/Users\/marwa\/eclipse-workspace\/KGB\/src\/test\/java\/com\/hrms\/testbase\/PageInitializer.java"},{"path":"\/HRMS-CUCUMBER\/src\/test\/resources\/Features","parentWorkspace":"C:\/Users\/marwa\/eclipse-workspace","name":"Dashboard.feature.feature","lastModified":1598730876561,"locationURI":"file:\/C:\/Users\/marwa\/eclipse-workspace\/HRMS-CUCUMBER\/src\/test\/resources\/Features\/Dashboard.feature.feature"},{"path":"\/com.syntax.Selenium\/src\/com\/syntax\/selenuim\/review\/Class01","parentWorkspace":"C:\/Users\/marwa\/eclipse-workspace","name":"CalendarHandeling.java","lastModified":1590802479975,"locationURI":"file:\/C:\/Users\/marwa\/eclipse-workspace\/com.syntax.Selenium\/src\/com\/syntax\/selenuim\/review\/Class01\/CalendarHandeling.java"},{"path":"\/HRMS-CUCUMBER\/src\/test\/java\/com\/hrms\/steps","parentWorkspace":"C:\/Users\/marwa\/eclipse-workspace","name":"SauceDemoLoginSteps.java","lastModified":1598916415194,"locationURI":"file:\/C:\/Users\/marwa\/eclipse-workspace\/HRMS-CUCUMBER\/src\/test\/java\/com\/hrms\/steps\/SauceDemoLoginSteps.java"},{"path":"\/com.syntax.Selenium\/src\/com\/syntax\/selenuim\/class01","parentWorkspace":"C:\/Users\/marwa\/eclipse-workspace","name":"LunchChromeBrowser.java","lastModified":1601921280362,"locationURI":"file:\/C:\/Users\/marwa\/eclipse-workspace\/com.syntax.Selenium\/src\/com\/syntax\/selenuim\/class01\/LunchChromeBrowser.java"},{"path":"\/HRMSFramework\/src\/test\/java\/com\/hrms\/testbase","parentWorkspace":"C:\/Users\/marwa\/eclipse-workspace","name":"ListenersDemo.java","lastModified":1596665798495,"locationURI":"file:\/C:\/Users\/marwa\/eclipse-workspace\/HRMSFramework\/src\/test\/java\/com\/hrms\/testbase\/ListenersDemo.java"},{"path":"\/HRMS-CUCUMBER\/src\/test\/java\/com\/hrms\/pages","parentWorkspace":"C:\/Users\/marwa\/eclipse-workspace","name":"SauceDemoLoginPage.java","lastModified":1598880847304,"locationURI":"file:\/C:\/Users\/marwa\/eclipse-workspace\/HRMS-CUCUMBER\/src\/test\/java\/com\/hrms\/pages\/SauceDemoLoginPage.java"},{"path":"\/com.syntax.Selenium\/src\/com\/pages","parentWorkspace":"C:\/Users\/marwa\/eclipse-workspace","name":"LoginPage.java","lastModified":1590951748845,"locationURI":"file:\/C:\/Users\/marwa\/eclipse-workspace\/com.syntax.Selenium\/src\/com\/pages\/LoginPage.java"},{"path":"\/HRMS-CUCUMBER\/src\/test\/java\/com\/hrms\/practice","parentWorkspace":"C:\/Users\/marwa\/eclipse-workspace","name":"Recap.java","lastModified":1600047369742,"locationURI":"file:\/C:\/Users\/marwa\/eclipse-workspace\/HRMS-CUCUMBER\/src\/test\/java\/com\/hrms\/practice\/Recap.java"},{"path":"\/HRMS-CUCUMBER\/src\/test\/java\/com\/hrms\/steps","parentWorkspace":"C:\/Users\/marwa\/eclipse-workspace","name":"AddEmployee.java","lastModified":1598730876561,"locationURI":"file:\/C:\/Users\/marwa\/eclipse-workspace\/HRMS-CUCUMBER\/src\/test\/java\/com\/hrms\/steps\/AddEmployee.java"},{"path":"\/com.syntax.Selenium\/src\/com\/syntax\/selenuim\/class11","parentWorkspace":"C:\/Users\/marwa\/eclipse-workspace","name":"FileUpload.java","lastModified":1590802463360,"locationURI":"file:\/C:\/Users\/marwa\/eclipse-workspace\/com.syntax.Selenium\/src\/com\/syntax\/selenuim\/class11\/FileUpload.java"},{"path":"\/HRMS-CUCUMBER\/src\/test\/java\/com\/hrms\/practice","parentWorkspace":"C:\/Users\/marwa\/eclipse-workspace","name":"enhancedDataStoring.java","lastModified":1600050666219,"locationURI":"file:\/C:\/Users\/marwa\/eclipse-workspace\/HRMS-CUCUMBER\/src\/test\/java\/com\/hrms\/practice\/enhancedDataStoring.java"},{"path":"\/com.syntax.Selenium\/src\/com\/syntax\/test","parentWorkspace":"C:\/Users\/marwa\/eclipse-workspace","name":"DashBoardPageElements.java","lastModified":1590956774001,"locationURI":"file:\/C:\/Users\/marwa\/eclipse-workspace\/com.syntax.Selenium\/src\/com\/syntax\/test\/DashBoardPageElements.java"},{"path":"\/com.syntax.Java\/configs","parentWorkspace":"C:\/Users\/marwa\/eclipse-workspace","name":"Examples.properties","lastModified":1596135578707,"locationURI":"file:\/C:\/Users\/marwa\/eclipse-workspace\/com.syntax.Java\/configs\/Examples.properties"},{"path":"\/HRMS-CUCUMBER\/src\/test\/java\/com\/hrms\/pages","parentWorkspace":"C:\/Users\/marwa\/eclipse-workspace","name":"AddEmployeePageElement.java","lastModified":1598470200020,"locationURI":"file:\/C:\/Users\/marwa\/eclipse-workspace\/HRMS-CUCUMBER\/src\/test\/java\/com\/hrms\/pages\/AddEmployeePageElement.java"},{"path":"\/HRMS-CUCUMBER\/src\/test\/java\/com\/hrms\/runners","parentWorkspace":"C:\/Users\/marwa\/eclipse-workspace","name":"TestRunner.java","lastModified":1598730360749,"locationURI":"file:\/C:\/Users\/marwa\/eclipse-workspace\/HRMS-CUCUMBER\/src\/test\/java\/com\/hrms\/runners\/TestRunner.java"},{"path":"\/HRMS-CUCUMBER\/src\/test\/java\/com\/hrms\/utils","parentWorkspace":"C:\/Users\/marwa\/eclipse-workspace","name":"DBUtils.java","lastModified":1600051301525,"locationURI":"file:\/C:\/Users\/marwa\/eclipse-workspace\/HRMS-CUCUMBER\/src\/test\/java\/com\/hrms\/utils\/DBUtils.java"},{"path":"\/HRMS-CUCUMBER\/src\/test\/java\/com\/hrms\/practice","parentWorkspace":"C:\/Users\/marwa\/eclipse-workspace","name":"MetaData.java","lastModified":1600046453521,"locationURI":"file:\/C:\/Users\/marwa\/eclipse-workspace\/HRMS-CUCUMBER\/src\/test\/java\/com\/hrms\/practice\/MetaData.java"},{"path":"\/HRMS-CUCUMBER\/src\/test\/java\/com\/hrms\/utils","parentWorkspace":"C:\/Users\/marwa\/eclipse-workspace","name":"CommonMethods.java","lastModified":1598373956203,"locationURI":"file:\/C:\/Users\/marwa\/eclipse-workspace\/HRMS-CUCUMBER\/src\/test\/java\/com\/hrms\/utils\/CommonMethods.java"},{"path":"\/HRMS-CUCUMBER\/src\/test\/java\/com\/hrms\/API\/steps\/practice","parentWorkspace":"C:\/Users\/marwa\/eclipse-workspace","name":"TokenGenerationSteps.java","lastModified":1599573305546,"locationURI":"file:\/C:\/Users\/marwa\/eclipse-workspace\/HRMS-CUCUMBER\/src\/test\/java\/com\/hrms\/API\/steps\/practice\/TokenGenerationSteps.java"},{"path":"\/HRMS-CUCUMBER\/src\/test\/resources\/Features","parentWorkspace":"C:\/Users\/marwa\/eclipse-workspace","name":"Login.feature","lastModified":1600057353974,"locationURI":"file:\/C:\/Users\/marwa\/eclipse-workspace\/HRMS-CUCUMBER\/src\/test\/resources\/Features\/Login.feature"},{"path":"\/HRMS-CUCUMBER\/src\/test\/resources\/configs","parentWorkspace":"C:\/Users\/marwa\/eclipse-workspace","name":"configuration.properties","lastModified":1603645702500,"locationURI":"file:\/C:\/Users\/marwa\/eclipse-workspace\/HRMS-CUCUMBER\/src\/test\/resources\/configs\/configuration.properties"},{"path":"\/HRMS-CUCUMBER\/src\/test\/java\/com\/hrms\/practice","parentWorkspace":"C:\/Users\/marwa\/eclipse-workspace","name":"JDBCDemo.java","lastModified":1599974544681,"locationURI":"file:\/C:\/Users\/marwa\/eclipse-workspace\/HRMS-CUCUMBER\/src\/test\/java\/com\/hrms\/practice\/JDBCDemo.java"},{"path":"\/com.syntax.Selenium\/src\/com\/syntax\/test","parentWorkspace":"C:\/Users\/marwa\/eclipse-workspace","name":"HrmsLogin.java","lastModified":1590952261653,"locationURI":"file:\/C:\/Users\/marwa\/eclipse-workspace\/com.syntax.Selenium\/src\/com\/syntax\/test\/HrmsLogin.java"},{"path":"\/HRMS-CUCUMBER\/src\/test\/java\/com\/hrms\/tdd","parentWorkspace":"C:\/Users\/marwa\/eclipse-workspace","name":"TDD.java","lastModified":1599761164686,"locationURI":"file:\/C:\/Users\/marwa\/eclipse-workspace\/HRMS-CUCUMBER\/src\/test\/java\/com\/hrms\/tdd\/TDD.java"},{"path":"\/com.syntax.Java\/src\/com\/syntax\/class33","parentWorkspace":"C:\/Users\/marwa\/eclipse-workspace","name":"HandlingException.java","lastModified":1594251148275,"locationURI":"file:\/C:\/Users\/marwa\/eclipse-workspace\/com.syntax.Java\/src\/com\/syntax\/class33\/HandlingException.java"},{"path":"\/HRMS-CUCUMBER\/src\/test\/java\/selenuimPractice","parentWorkspace":"C:\/Users\/marwa\/eclipse-workspace","name":"DropDwonDemo.java","lastModified":1602011341882,"locationURI":"file:\/C:\/Users\/marwa\/eclipse-workspace\/HRMS-CUCUMBER\/src\/test\/java\/selenuimPractice\/DropDwonDemo.java"},{"path":"\/com.syntax.Selenium\/src\/com\/syntax\/selenuim\/class05","parentWorkspace":"C:\/Users\/marwa\/eclipse-workspace","name":"DropDownDemo.java","lastModified":1592161022553,"locationURI":"file:\/C:\/Users\/marwa\/eclipse-workspace\/com.syntax.Selenium\/src\/com\/syntax\/selenuim\/class05\/DropDownDemo.java"},{"path":"\/HRMS-CUCUMBER\/src\/test\/resources\/Features","parentWorkspace":"C:\/Users\/marwa\/eclipse-workspace","name":"SearchEmployee.feature","lastModified":1598814546590,"locationURI":"file:\/C:\/Users\/marwa\/eclipse-workspace\/HRMS-CUCUMBER\/src\/test\/resources\/Features\/SearchEmployee.feature"},{"path":"\/com.syntax.Selenium\/configs","parentWorkspace":"C:\/Users\/marwa\/eclipse-workspace","name":"configuration.properties","lastModified":1590952055289,"locationURI":"file:\/C:\/Users\/marwa\/eclipse-workspace\/com.syntax.Selenium\/configs\/configuration.properties"},{"path":"\/com.syntax.Selenium\/src\/com\/syntax\/test","parentWorkspace":"C:\/Users\/marwa\/eclipse-workspace","name":"LoginPageTest.java","lastModified":1591145811188,"locationURI":"file:\/C:\/Users\/marwa\/eclipse-workspace\/com.syntax.Selenium\/src\/com\/syntax\/test\/LoginPageTest.java"},{"path":"\/HRMS-CUCUMBER\/src\/test\/java\/com\/hrms\/testbase","parentWorkspace":"C:\/Users\/marwa\/eclipse-workspace","name":"BaseClass.java","lastModified":1603646058617,"locationURI":"file:\/C:\/Users\/marwa\/eclipse-workspace\/HRMS-CUCUMBER\/src\/test\/java\/com\/hrms\/testbase\/BaseClass.java"},{"path":"\/HRMS-CUCUMBER","parentWorkspace":"C:\/Users\/marwa\/eclipse-workspace","name":"pom.xml","lastModified":1599969665433,"locationURI":"file:\/C:\/Users\/marwa\/eclipse-workspace\/HRMS-CUCUMBER\/pom.xml"},{"path":"\/KGB\/src\/test\/java\/com\/hrms\/steps","parentWorkspace":"C:\/Users\/marwa\/eclipse-workspace","name":"SauceDemoLoginSteps.java","lastModified":1597367852148,"locationURI":"file:\/C:\/Users\/marwa\/eclipse-workspace\/KGB\/src\/test\/java\/com\/hrms\/steps\/SauceDemoLoginSteps.java"},{"path":"\/HRMS-CUCUMBER\/src\/test\/resources\/Features","parentWorkspace":"C:\/Users\/marwa\/eclipse-workspace","name":"SauceDemoLoginWithDataTable.feature","lastModified":1599053502065,"locationURI":"file:\/C:\/Users\/marwa\/eclipse-workspace\/HRMS-CUCUMBER\/src\/test\/resources\/Features\/SauceDemoLoginWithDataTable.feature"},{"path":"\/HRMS-CUCUMBER\/src\/test\/java\/com\/hrms\/API\/steps\/practice","parentWorkspace":"C:\/Users\/marwa\/eclipse-workspace","name":"WorkflowAllSteps.java","lastModified":1600054017448,"locationURI":"file:\/C:\/Users\/marwa\/eclipse-workspace\/HRMS-CUCUMBER\/src\/test\/java\/com\/hrms\/API\/steps\/practice\/WorkflowAllSteps.java"},{"path":"\/HRMS-CUCUMBER\/src\/test\/resources\/Features","parentWorkspace":"C:\/Users\/marwa\/eclipse-workspace","name":"APIWorkflow.feature","lastModified":1600705122419,"locationURI":"file:\/C:\/Users\/marwa\/eclipse-workspace\/HRMS-CUCUMBER\/src\/test\/resources\/Features\/APIWorkflow.feature"},{"path":"\/HRMS-CUCUMBER\/src\/test\/resources\/Features","parentWorkspace":"C:\/Users\/marwa\/eclipse-workspace","name":"UIvsDatabaseValidation.feature","lastModified":1600057353974,"locationURI":"file:\/C:\/Users\/marwa\/eclipse-workspace\/HRMS-CUCUMBER\/src\/test\/resources\/Features\/UIvsDatabaseValidation.feature"},{"path":"\/HRMS-CUCUMBER\/src\/test\/java\/com\/hrms\/pages","parentWorkspace":"C:\/Users\/marwa\/eclipse-workspace","name":"ViewEmployeePageElements.java","lastModified":1600056227963,"locationURI":"file:\/C:\/Users\/marwa\/eclipse-workspace\/HRMS-CUCUMBER\/src\/test\/java\/com\/hrms\/pages\/ViewEmployeePageElements.java"},{"path":"\/HRMS-CUCUMBER\/src\/test\/java\/com\/hrms\/runners","parentWorkspace":"C:\/Users\/marwa\/eclipse-workspace","name":"SingleTestRunner.java","lastModified":1598914564354,"locationURI":"file:\/C:\/Users\/marwa\/eclipse-workspace\/HRMS-CUCUMBER\/src\/test\/java\/com\/hrms\/runners\/SingleTestRunner.java"},{"path":"\/HRMSFramework\/src\/test\/java\/com\/hrms\/utils","parentWorkspace":"C:\/Users\/marwa\/eclipse-workspace","name":"CommonMethods.java","lastModified":1596821043818,"locationURI":"file:\/C:\/Users\/marwa\/eclipse-workspace\/HRMSFramework\/src\/test\/java\/com\/hrms\/utils\/CommonMethods.java"},{"path":"\/HRMS-CUCUMBER\/src\/test\/java\/com\/hrms\/pages","parentWorkspace":"C:\/Users\/marwa\/eclipse-workspace","name":"DashBoardPageElements.java","lastModified":1597684034219,"locationURI":"file:\/C:\/Users\/marwa\/eclipse-workspace\/HRMS-CUCUMBER\/src\/test\/java\/com\/hrms\/pages\/DashBoardPageElements.java"},{"path":"\/KGB\/src\/test\/resources\/Features","parentWorkspace":"C:\/Users\/marwa\/eclipse-workspace","name":"Marwa.feature","lastModified":1597367852148,"locationURI":"file:\/C:\/Users\/marwa\/eclipse-workspace\/KGB\/src\/test\/resources\/Features\/Marwa.feature"},{"path":"\/HRMS-CUCUMBER\/src\/test\/java\/com\/hrms\/pages","parentWorkspace":"C:\/Users\/marwa\/eclipse-workspace","name":"PersonDetailsPageElements.java","lastModified":1597374853094,"locationURI":"file:\/C:\/Users\/marwa\/eclipse-workspace\/HRMS-CUCUMBER\/src\/test\/java\/com\/hrms\/pages\/PersonDetailsPageElements.java"},{"path":"\/HRMS-CUCUMBER\/src\/test\/java\/com\/hrms\/API\/steps\/practice","parentWorkspace":"C:\/Users\/marwa\/eclipse-workspace","name":"HardCodeExamples.java","lastModified":1599586255393,"locationURI":"file:\/C:\/Users\/marwa\/eclipse-workspace\/HRMS-CUCUMBER\/src\/test\/java\/com\/hrms\/API\/steps\/practice\/HardCodeExamples.java"},{"path":"\/HRMS-CUCUMBER\/src\/test\/java\/selenuimPractice","parentWorkspace":"C:\/Users\/marwa\/eclipse-workspace","name":"HandelAlert.java","lastModified":1602299544869,"locationURI":"file:\/C:\/Users\/marwa\/eclipse-workspace\/HRMS-CUCUMBER\/src\/test\/java\/selenuimPractice\/HandelAlert.java"},{"path":"\/HRMS-CUCUMBER\/src\/test\/java\/com\/hrms\/practice","parentWorkspace":"C:\/Users\/marwa\/eclipse-workspace","name":"StoringData.java","lastModified":1600048510778,"locationURI":"file:\/C:\/Users\/marwa\/eclipse-workspace\/HRMS-CUCUMBER\/src\/test\/java\/com\/hrms\/practice\/StoringData.java"},{"path":"\/com.syntax.Selenium\/src\/com\/syntax\/test","parentWorkspace":"C:\/Users\/marwa\/eclipse-workspace","name":"LoginWithAdvancedXpath.java","lastModified":1590941867953,"locationURI":"file:\/C:\/Users\/marwa\/eclipse-workspace\/com.syntax.Selenium\/src\/com\/syntax\/test\/LoginWithAdvancedXpath.java"},{"path":"\/HRMS-CUCUMBER\/src\/test\/java\/selenuimPractice","parentWorkspace":"C:\/Users\/marwa\/eclipse-workspace","name":"DropDownDemo1.java","lastModified":1602016641835,"locationURI":"file:\/C:\/Users\/marwa\/eclipse-workspace\/HRMS-CUCUMBER\/src\/test\/java\/selenuimPractice\/DropDownDemo1.java"},{"path":"\/HRMS-CUCUMBER\/src\/test\/java\/com\/hrms\/runners","parentWorkspace":"C:\/Users\/marwa\/eclipse-workspace","name":"APIWorkflowRunner.java","lastModified":1599703146347,"locationURI":"file:\/C:\/Users\/marwa\/eclipse-workspace\/HRMS-CUCUMBER\/src\/test\/java\/com\/hrms\/runners\/APIWorkflowRunner.java"},{"path":"\/HRMS-CUCUMBER\/src\/test\/java\/com\/hrms\/utils","parentWorkspace":"C:\/Users\/marwa\/eclipse-workspace","name":"GlobalVariables.java","lastModified":1600057245781,"locationURI":"file:\/C:\/Users\/marwa\/eclipse-workspace\/HRMS-CUCUMBER\/src\/test\/java\/com\/hrms\/utils\/GlobalVariables.java"},{"path":"\/KGB\/src\/test\/resources\/Features","parentWorkspace":"C:\/Users\/marwa\/eclipse-workspace","name":"story_19.feature","lastModified":1597367852148,"locationURI":"file:\/C:\/Users\/marwa\/eclipse-workspace\/KGB\/src\/test\/resources\/Features\/story_19.feature"},{"path":"\/com.syntax.Java\/src\/com\/syntax\/class08","parentWorkspace":"C:\/Users\/marwa\/eclipse-workspace","name":"LoopReview.java","lastModified":1595523399520,"locationURI":"file:\/C:\/Users\/marwa\/eclipse-workspace\/com.syntax.Java\/src\/com\/syntax\/class08\/LoopReview.java"},{"path":"\/HRMS-CUCUMBER\/src\/test\/resources\/Features","parentWorkspace":"C:\/Users\/marwa\/eclipse-workspace","name":"AddEmploye.feature","lastModified":1599702955239,"locationURI":"file:\/C:\/Users\/marwa\/eclipse-workspace\/HRMS-CUCUMBER\/src\/test\/resources\/Features\/AddEmploye.feature"},{"path":"\/HRMS-CUCUMBER\/src\/test\/java\/com\/hrms\/steps","parentWorkspace":"C:\/Users\/marwa\/eclipse-workspace","name":"DBSteps.java","lastModified":1600057270051,"locationURI":"file:\/C:\/Users\/marwa\/eclipse-workspace\/HRMS-CUCUMBER\/src\/test\/java\/com\/hrms\/steps\/DBSteps.java"},{"path":"\/HRMS-CUCUMBER\/src\/test\/resources\/Features","parentWorkspace":"C:\/Users\/marwa\/eclipse-workspace","name":"SauceDemoLoginWithExample.feature","lastModified":1599053502065,"locationURI":"file:\/C:\/Users\/marwa\/eclipse-workspace\/HRMS-CUCUMBER\/src\/test\/resources\/Features\/SauceDemoLoginWithExample.feature"},{"path":"\/HRMS-CUCUMBER\/src\/test\/java\/com\/hrms\/steps","parentWorkspace":"C:\/Users\/marwa\/eclipse-workspace","name":"UIvsDatabaseValidation.java","lastModified":1599136155516,"locationURI":"file:\/C:\/Users\/marwa\/eclipse-workspace\/HRMS-CUCUMBER\/src\/test\/java\/com\/hrms\/steps\/UIvsDatabaseValidation.java"},{"path":"\/com.syntax.Selenium\/src\/com\/syntax\/utils","parentWorkspace":"C:\/Users\/marwa\/eclipse-workspace","name":"CommonMethods.java","lastModified":1590947981069,"locationURI":"file:\/C:\/Users\/marwa\/eclipse-workspace\/com.syntax.Selenium\/src\/com\/syntax\/utils\/CommonMethods.java"},{"path":"\/HRMS-CUCUMBER\/src\/test\/java\/com\/hrms\/steps","parentWorkspace":"C:\/Users\/marwa\/eclipse-workspace","name":"Login.java","lastModified":1598813012082,"locationURI":"file:\/C:\/Users\/marwa\/eclipse-workspace\/HRMS-CUCUMBER\/src\/test\/java\/com\/hrms\/steps\/Login.java"},{"path":"\/HRMS-CUCUMBER\/src\/test\/resources\/TestData","parentWorkspace":"C:\/Users\/marwa\/eclipse-workspace","name":"Test.xlsx","lastModified":1591755068547,"locationURI":"file:\/C:\/Users\/marwa\/eclipse-workspace\/HRMS-CUCUMBER\/src\/test\/resources\/TestData\/Test.xlsx"},{"path":"\/HRMS-CUCUMBER\/src\/test\/resources\/Features","parentWorkspace":"C:\/Users\/marwa\/eclipse-workspace","name":"Sample.feature","lastModified":1598813683993,"locationURI":"file:\/C:\/Users\/marwa\/eclipse-workspace\/HRMS-CUCUMBER\/src\/test\/resources\/Features\/Sample.feature"}]}